tests/__init__.py
tests/test_soap_client.py
zephyr_soap/__init__.py
zephyr_soap/core.py
zephyr_soap-0.1.4.dist-info/LICENSE
zephyr_soap-0.1.4.dist-info/METADATA
zephyr_soap-0.1.4.dist-info/WHEEL
zephyr_soap-0.1.4.dist-info/top_level.txt
zephyr_soap-0.1.4.dist-info/RECORD
