Metadata-Version: 2.1
Name: zephyr_soap
Version: 0.1.4
Summary: Client SOAP pour utiliser les services SOAP d'Enedis
Home-page: https://github.com/ZephyrIt0/Zephyr_soap_librairie
Author: gld
Author-email: dimbugrace@gmail.com
Classifier: Programming Language :: Python :: 3
Classifier: License :: OSI Approved :: MIT License
Classifier: Operating System :: OS Independent
Requires-Python: >=3.6
License-File: LICENSE
Requires-Dist: requests
Requires-Dist: zeep
Requires-Dist: pytz
